{
 "54be84343063641c1f00153f_11": {
  "c0": "An HMHVV deathmatch. Admit it, Seattle - you'd pay to watch that."
 },
 "54d96c4e3030316814006f9b_226": {
  "c0": "Ha. Funny, Seattle."
 },
 "54f4d9223430612012004418_10": {
  "c0": "This lunk's got even more spice than Duncan."
 },
 "54d96b813030316814006f66_147": {
  "c0": "Hey. You're back."
 },
 "54d96b813030316814006f66_286": {
  "c0": "Hey. You're back."
 },
 "54d96b813030316814006f66_310": {
  "c0": "Hey. You're back."
 },
 "54d96b813030316814006f66_326": {
  "c0": "Hey. You're back."
 },
 "54d96b813030316814006f66_343": {
  "c0": "Hey. You're back."
 },
 "55369fa7323437682800451d_13": {
  "c0": "Listen. We have a problem."
 },
 "556cf8753234312c01003971_3": {
  "c0": "Hey, it's me."
 },
 "556d45c26433612807001ecb_17": {
  "c0": "Seriously... why do you destroy everything you touch?"
 },
 "5570e6b6323431541e005e1d_39": {
  "c0": "Hey... I'm gonna need some backup."
 },
 "557650c5623666c02b003595_64": {
  "c0": "Emilie, this is the person I told you about. They need the software you developed to inhibit your cortical implant. They can also be kind of blunt."
 },
 "559ec0526236669809002374_123": {
  "c0": "Do you understand what you're saying?! The source isn't just a thing. It's a Yama King. A demon goddess."
 },
 "559ec0526236669809002374_127": {
  "c1": "It's not just a thing in there. It's a Yama King. A demon goddess."
 },
 "56004032626632e01500452a_11": {
  "c0": "Like hell we are! Don't get cocky - we've got to keep our heads clear until this situation has been resolved."
 },
 "56218ac8306364fc18005d11_20": {
  "c0": "Shit. We're heading down the wrong track. We branched right back there. We need to be going left."
 },
 "54d96ae73030316814006f45_18": {
  "c1": "Well, maybe not for this one, here. They've had a harder road than me."
 },
 "54d96ae73030316814006f45_58": {
  "c1": "Time for bed. I think we both deserve a good night's sleep. Get out of here. I'll see you in the morning."
 },
 "54d96ae73030316814006f45_59": {
  "c1": "Time for bed. I think we both deserve a good night's sleep. Get out of here. I'll see you in the morning."
 },
 "54d96ae73030316814006f45_60": {
  "c1": "Time for bed. I think we both deserve a good night's sleep. Get out of here. I'll see you in the morning."
 },
 "54d96ae73030316814006f45_66": {
  "c1": "Time for bed. I think we deserve a good night's sleep. Get out of here. I'll see you in the morning."
 },
 "54d96ae73030316814006f45_67": {
  "c1": "Time for bed. I think we deserve a good night's sleep. Get out of here. I'll see you in the morning."
 },
 "54d96ae73030316814006f45_68": {
  "c1": "Time for bed. I think we deserve a good night's sleep. Get out of here. I'll see you in the morning."
 },
 "54d96ae73030316814006f45_69": {
  "c1": "Time for bed. I think we deserve a good night's sleep. Get out of here. I'll see you in the morning."
 },
 "54d96ae73030316814006f45_102": {
  "c1": "We really went in different directions - you to jail and me to Lone Star."
 },
 "54d96ae73030316814006f45_191": {
  "c0": "Yeah, I was. But I got a lot better when we found a squat together, and even better later when we went to live with Ray. I was still a violent son of a bitch, but basically under control. That was because of you. You were the voice of reason. And the brains."
 },
 "54d96ae73030316814006f45_192": {
  "c0": "Pretty nasty. But that was before we met. When we squatted together, and later when we were living with Ray, I was still a violent son of a bitch, but basically under control. That was because of you. You were the voice of reason. And the brains."
 },
 "54d96ae73030316814006f45_211": {
  "c0": "I'm sorry, did you just give me sage advice? Sounds like you did some growing up of your own."
 },
 "54d96ae73030316814006f45_310": {
  "c0": "Okay, boss, we don't need to do things my way. No need for us to butt heads."
 },
 "54d96ae73030316814006f45_451": {
  "c0": "I still can't believe that you made a deal with that thing. I mean, it was a mummy. You don't make deals with mummies!"
 },
 "54d96ae73030316814006f45_469": {
  "c0": "That was a choice. If you'd gotten more than a couple of episodes in, you'd've learned that she was a Bunraku puppet in the beginning, and that her real personality was being suppressed. Man. So many great twists in that show. After this is all over, you should go back and give it a watch... a real watch this time."
 },
 "54da5dc6306364a88e0035ea_3": {
  "c0": "That's the kind of thing I like to hear - nothing but the weather. As long as we don't get into a fight down here, we'll stay clear of trouble. Any gunfire will get their attention, and fast."
 },
 "55495f8a303031a814005481_1": {
  "c0": "Hey! C'mon, wake up! We gotta go talk to Kindly. The others have already left."
 },
 "55496bb3303031a8140055ca_105": {
  "c0": "Gonna be weird calling you that again. Haven't called you that since we were kids."
 },
 "555a5164323437080f00276b_67": {
  "c0": "Hey..."
 },
 "55820d1c623666c8260088b7_15": {
  "c1": "We're both here."
 },
 "559ec0526236669809002374_117": {
  "c0": "That's right. We owe you, Raymond, and I'm not walking away from that. I'll help you fix your mess or die trying. Then we'll be even."
 },
 "54d96be03030316814006f7f_1": {
  "c0": "It is not every day that one can say they fought an ancient god - and won."
 },
 "54d96be03030316814006f7f_396": {
  "c0": "I am ready to go when you are - but it doesn't hurt to do a last minute inspection. Message me from the MTR station when you are ready."
 },
 "54d96be03030316814006f7f_397": {
  "c0": "Have you changed your mind about the run I proposed?"
 },
 "54e6531030636444140071ff_38": {
  "c0": "I wonder - what are you planning? To double-cross the double-crosser? Or to isolate our mystery friend and remove that threat on your terms?"
 },
 "556740a732343744370063d1_23": {
  "c0": "You have my deepest sympathies, Tanjiro. But my friend is right - for us to stay safe, we cannot leave any witnesses."
 },
 "566f69ef6436613815007c49_34": {
  "c0": "It seems to me that we're about to take a leap into a whole new world, my friend, and I'm certain that it will be interesting, whatever we choose to do. Adventure and fortune, or misfortune, depending on your viewpoint, seem to follow us wherever we go."
 },
 "5601e315626632941e0014eb_4": {
  "c0": "Little bird. I trust that you're doing well, and keeping your eyes and ears open like I told you."
 },
 "54c696f3303031301d005190_34": {
  "c0": "Ah, like little Is0bel here! I can't imagine traveling the Matrix. And how did you become a decker, dear."
 },
 "54c696f3303031301d005190_56": {
  "c0": "Who knows, dear? It could have been drugs but he was lucid most of the time. Still, if Mr. Black was on something, it was definitely some sort of hallucinogen."
 },
 "54c696f3303031301d005190_59": {
  "c0": "Perhaps you misunderstand our relationship, my sweet. You don't interview me, I interview you. But, I will indulge this one question, since poor Duncan Wu here looks so worried."
 },
 "54c696f3303031301d005190_61": {
  "c0": "Perhaps you misunderstand our relationship, my sweet. You don't interview me, I interview you. But, I will indulge this one question, since poor Duncan Wu here looks so worried."
 },
 "54c696f3303031301d005190_122": {
  "c1": "It's a good name. Has real character."
 },
 "55496bb3303031a8140055ca_85": {
  "c1": "First order of business - you and Duncan Wu don't exist anymore. You'll need street names."
 },
 "55496bb3303031a8140055ca_111": {
  "c1": "First order of business. Our friend here has already chosen a street name."
 },
 "55b3d7776236668819001370_4": {
  "c0": "Little bird. I figured you were dead. Last I heard, my soldiers had found you and everyone was heading into the Walled City. Then things got out of control."
 },
 "55b3d7776236668819001370_16": {
  "c1": "I'm down five soldiers. Vice numbers are gonna drop. Loans won't get repaid. I've taken losses, little bird."
 },
 "55b3d7776236668819001370_43": {
  "c0": "Tell our friend here what that means, Mr. Bao."
 },
 "55b3d7776236668819001370_98": {
  "c0": "Little bird. I figured you were dead. Last I heard, my soldiers had found you and everyone was heading into the Walled City. Then things got out of control."
 },
 "55b3d7776236668819001370_109": {
  "c1": "I'm down five soldiers. Vice numbers are gonna drop. Loans won't get repaid. I've taken losses, little bird."
 },
 "55b3d7776236668819001370_127": {
  "c0": "Tell our friend here what that means, Mr. Bao."
 },
 "54d545e23030312c0c00300c_1": {
  "c0": "Hey! I can't talk. I've got a whole buncha--"
 },
 "54d545e23030312c0c00300c_19": {
  "c0": "Hey... boy, it's good to see you..."
 },
 "54d545e23030312c0c00300c_57": {
  "c0": "Hey... I'm doing some delicate work here. Just reaching a good point to pause, actually. Okay... what's up?"
 },
 "54d545e23030312c0c00300c_66": {
  "c0": "Oh... hey. Ugh... what can I do you for?"
 },
 "554693e9393936841900720a_0": {
  "c0": "Ermine's eyes are bleary. Blood from a recent nosebleed speckles her upper lip. You need armor? Ammunition? Painkillers?"
 },
 "554693e9393936841900720a_147": {
  "c0": "You... I thought you were lost to us, too."
 },
 "54d5743c3030314013003009_2": {
  "c0": "Yo. 'Sup."
 },
 "54d5743c3030314013003009_24": {
  "c0": "Hi... yo... hey."
 },
 "54d5743c3030314013003009_80": {
  "c0": "Yo! What's going on? What have you been up to?"
 },
 "54d5743c3030314013003009_102": {
  "c0": "Yo. Thanks for talking to me."
 },
 "54d5743c3030314013003009_153": {
  "c1": "You're someone who appreciates the good stuff. I like that."
 },
 "54d5743c3030314013003009_296": {
  "c0": "Man...If this true, and it sounds like you've got enough evidence that it probably is..."
 },
 "54d5743c3030314013003009_301": {
  "c0": "Yo!...That shit is BANNED! Lift it off some Yellow Lotus? They traffic this stuff... de-limited sim chips, full sensory experiences. You looking for a buyer? I can make it HAPPEN. How's a fat stack of nuyen sound?"
 },
 "54d579a43030314013003045_10": {
  "c0": "Thank you."
 },
 "54d579a43030314013003045_220": {
  "c0": "It's you."
 },
 "54d579a43030314013003045_223": {
  "c1": "That doesn't matter. Listen, I found it - the thing we've been searching for. I know what's happening inside the Walled City."
 },
 "554158bb3234370819002cee_20": {
  "c0": "Goodbye, my child."
 },
 "554158bb3234370819002cee_24": {
  "c0": "And... one more thing..."
 },
 "555a5164323437080f00276b_72": {
  "c0": "Thank you for c-coming to Hong Kong... for helping me to see this through. You have always been... like a son to me... regardless of our d-difficulties."
 },
 "55820d1c623666c8260088b7_6": {
  "c1": "Old... tired. Hello... my child."
 },
 "55820d1c623666c8260088b7_16": {
  "c0": "Hello... my child. Good to...see you."
 },
 "55820d1c623666c8260088b7_17": {
  "c0": "You... you came."
 },
 "55820d1c623666c8260088b7_18": {
  "c1": "Thank you... for coming... my child."
 },
 "55820d1c623666c8260088b7_20": {
  "c0": "You...?"
 },
 "55820d1c623666c8260088b7_22": {
  "c0": "You... you came."
 },
 "558898d6623666a012005538_23": {
  "c0": "The... t-time for t-timidity is over, my child. No m-more cowardice. It's time for me to finally... t-t-take action."
 },
 "558898d6623666a012005538_24": {
  "c0": "I do, my child. It's t-time for me to finally... take action. No more c-cowardice."
 },
 "558898d6623666a012005538_27": {
  "c0": "I don't want to be s-separated from you either...",
  "c1": "... but you are the r-right person to lead the first team... higher chance of success this way. If we go in one group... one chance at success. But, if the first team is lost... th"
 },
 "5589c2fc623666fc370055a8_1": {
  "c0": "You look l-like you have... something on your... m-mind."
 },
 "559ec0526236669809002374_18": {
  "c0": "Y-you came."
 },
 "559ec0526236669809002374_32": {
  "c0": "I understand the f-feeling... It was only recently... that I f-figured out what was going on."
 },
 "54d56f243030316013003007_115": {
  "c0": "Beautiful... here's looking at you!"
 },
 "54d56f243030316013003007_142": {
  "c0": "That was real... I mean real, beautiful! You've got some chops on you. Whew!"
 },
 "563e7751643661b00e0012c3_0": {
  "c0": "You're alive! What the hell is going on here?"
 },
 "566213356436616013004496_13": {
  "c0": "That'd be a mistake. Use your head - Krait's people are getting paid to kill us, not engage us in a polite chat."
 },
 "5668ba94643661cc120023e7_30": {
  "c0": "Listen... I can't help you. Another hit of drain might kill me."
 },
 "55e8b58a643661a812007a17_3": {
  "c0": "Good morning."
 },
 "55369fa7323437682800451d_29": {
  "c0": "You ask your questions... I'll answer them as efficiently as I can. When we're done, I'll shake hands with a stranger and walk away wondering what just happened."
 },
 "56003452626632e015004444_55": {
  "c0": "A lot better than yours."
 },
 "560591ce643661d4160012fc_1": {
  "c0": "You there."
 },
 "555a5164323437080f00276b_71": {
  "c0": "Thank you for c-coming to Hong Kong... for helping me to see this through. You have always been... like a daughter to me... regardless of our d-difficulties."
 },
 "55455138656333641b003bab_31": {
  "c0": "You're here."
 },
 "56097ecf643661801100391d_1": {
  "c0": "Aah, you're here, very good. I am Senior Inspector Andy Lam, one of the leaders of this task force. Thank you for coming so promptly."
 },
 "5609dc5c643661e00e007ff7_86": {
  "c0": "Nobody's threatening you. Senior Inspector Qiu was just being careful. As long as you don't try to screw us over, you've got nothing to worry about."
 },
 "5600340a626632e015004432_52": {
  "c1": "You wanna go around pretending to be the Big-Time Criminal, you knock yourself out. To me, you're the name on the form."
 },
 "54dbe9e13030316c15006ca2_67": {
  "c0": "You know, young one... yes, you... you look very much like the person I saw walking that hall. They moved steadily down the path, walking at an even pace. And just behind them, a great and terrible shadow followed."
 },
 "54dbe9e13030316c15006ca2_83": {
  "c0": "Enough of that, Gin. Our young friend here asked in earnest for our advice. They deserve a proper response."
 },
 "54dbe9e13030316c15006ca2_148": {
  "c0": "I feel it, too. The change. But what we're changing into, I don't know. It's just like in my dream... We're sitting on the threshold of something great. Great, and terrible. If you can get to the bottom of this, there'll be more than just us Go players eager to thank you. But, please. Hurry."
 },
 "54dbe9e13030316c15006ca2_150": {
  "c0": "Long time, no see."
 },
 "54dbe9e13030316c15006ca2_157": {
  "c0": "Long time, no see."
 },
 "55a7e9de6236664014000aa4_42": {
  "c0": "Good luck. You look like just the type to do it."
 },
 "55a7e9de6236664014000aa4_78": {
  "c0": "Good luck. You look like just the type to do it."
 },
 "5668ba94643661cc120023e7_25": {
  "c0": "Hello, shadowrunner. Hello, Senior Inspector Qiu. Welcome to the future site of the Toho Harbor Complex."
 },
 "5668ba94643661cc120023e7_26": {
  "c0": "Hello, shadowrunner. Hello, Senior Inspector Qiu."
 },
 "562fe16f6436613011007f9b_16": {
  "c0": "Yes! Yes! Right away."
 },
 "54ff5820306364a01b004921_14": {
  "c0": "Wait a minute... I recognize you. You're that runner, right? Your name's all over the shadows of Hong Kong. From what I hear, you've been doing a lot of work for Kindly Cheng."
 },
 "54dbe9e13030316c15006ca2_127": {
  "c0": "I, for one, enjoy our young friend's visits."
 },
 "54dbe9e13030316c15006ca2_156": {
  "c0": "I, for one, enjoy our young friend's visits."
 },
 "552c2a54306364300300505f_0": {
  "c0": "That's far enough, pal."
 },
 "569ecd67306364a81f00521a_1": {
  "c0": "You must be the runner from Heoi. Heard about that dust-up at the Tigers' Den - glad to see that you got out alive."
 },
 "54da5dae306364a88e0035e1_37": {
  "c0": "So. You've been making a lot of waves lately, haven't you? Naughty, naughty."
 },
 "54da5dae306364a88e0035e1_38": {
  "c0": "My name is Hwang Jae-Min. I run the Blue Heaven Seoulpa Ring. I know who you are, and you've just stolen from Eastern Tiger."
 },
 "5525b2803063644415002063_2": {
  "c0": "Your wish is my command, my friend!"
 },
 "54bd54a5306364641300167d_1": {
  "c0": "What brings you to our little soirée, Argyle? I don't believe I've seen you around the studio before."
 },
 "5581d35e3234375439001ad9_13": {
  "c1": "Will this be sufficient, mortal? Will you accept my offer?"
 },
 "55aff6d0306364c414007270_17": {
  "g0": "Aljernon inclines his head politely."
 },
 "563e8d70643661b00e001344_1": {
  "c0": "Sorry about this. If there were another way, I would've taken it. You know how it is. Nothing personal."
 },
 "54da97d0653937300b002dc0_9": {
  "c0": "This is the Shangri-La. We have over two dozen private dining rooms in addition to our main dining floor. As I've already said, I serve out here. Your friend could be in any of our other rooms. Now, excuse me, I need to place these orders. Enjoy your meal."
 },
 "54da97d0653937300b002dc0_10": {
  "c0": "This is the Shangri-La. We have over two dozen private dining rooms in addition to our main dining floor. As I've already said, I serve out here. Your friend could be in any of our other rooms. Now, excuse me, I need to place these orders. Enjoy your meal."
 },
 "555a61da323431501900164e_31": {
  "c1": "Th-thank you."
 },
 "5693de1c3063641c0e0012f0_12": {
  "c0": "And you couldn't just buy a bottle in one of the convenience stores out there? C'mon, pal. Get the hell out of here before I throw you out."
 },
 "54e39226653937d419000f48_0": {
  "c0": "Hey. Is this your channel?"
 },
 "560475116436614812001385_1": {
  "c0": "Automated Health Service Station (#1-7730S) Patient Recognized as: Male:: Adult."
 },
 "560475116436614812001385_5": {
  "c0": "Automated Health Service Station (#1-7730S) Patient Recognized as: Female:: Adult."
 }
}